concise/__init__.py
concise/client.py
concise/exceptions.py
concise/openai_wrapper.py
concise/types.py
concise_sdk-1.1.0.dist-info/METADATA
concise_sdk-1.1.0.dist-info/WHEEL
concise_sdk-1.1.0.dist-info/top_level.txt
concise_sdk-1.1.0.dist-info/RECORD
