Metadata-Version: 2.4
Name: concise-sdk
Version: 1.1.0
Summary: Official Python SDK for Concise - Token compression for LLMs
Home-page: https://github.com/concise/python-sdk
Author: Concise Team
Author-email: support@concise.dev
Project-URL: Documentation, https://docs.concise.dev
Project-URL: Source, https://github.com/concise/python-sdk
Project-URL: Bug Reports, https://github.com/concise/python-sdk/issues
Keywords: llm,compression,openai,tokens,ai,nlp
Classifier: Development Status :: 4 - Beta
Classifier: Intended Audience :: Developers
Classifier: Topic :: Software Development :: Libraries :: Python Modules
Classifier: License :: OSI Approved :: MIT License
Classifier: Programming Language :: Python :: 3
Classifier: Programming Language :: Python :: 3.8
Classifier: Programming Language :: Python :: 3.9
Classifier: Programming Language :: Python :: 3.10
Classifier: Programming Language :: Python :: 3.11
Classifier: Programming Language :: Python :: 3.12
Requires-Python: >=3.8
Requires-Dist: httpx>=0.25.0
Provides-Extra: dev
Requires-Dist: pytest>=7.0.0; extra == "dev"
Requires-Dist: pytest-asyncio>=0.21.0; extra == "dev"
Requires-Dist: black>=23.0.0; extra == "dev"
Requires-Dist: mypy>=1.0.0; extra == "dev"
Dynamic: author
Dynamic: author-email
Dynamic: classifier
Dynamic: description
Dynamic: description-content-type
Dynamic: home-page
Dynamic: keywords
Dynamic: project-url
Dynamic: provides-extra
Dynamic: requires-dist
Dynamic: requires-python
Dynamic: summary
